lighthouse/__init__.py
lighthouse/client.py
lighthouse_private_markets_sdk-0.1.7.dist-info/METADATA
lighthouse_private_markets_sdk-0.1.7.dist-info/WHEEL
lighthouse_private_markets_sdk-0.1.7.dist-info/licenses/LICENSE
lighthouse_private_markets_sdk-0.1.7.dist-info/RECORD
