Metadata-Version: 2.4
Name: lighthouse-private-markets-sdk
Version: 0.1.7
Summary: Python SDK for Lighthouse Private Markets API with PostgREST-style querying
Project-URL: Homepage, https://github.com/lighthouse-app/lighthouse-private-markets-sdk
Project-URL: Repository, https://github.com/lighthouse-app/lighthouse-private-markets-sdk.git
Author-email: Alberto Marzetta <hello@trylighthouse.vc>
License-Expression: MIT
License-File: LICENSE
Classifier: Development Status :: 3 - Alpha
Classifier: Intended Audience :: Developers
Classifier: License :: OSI Approved :: MIT License
Classifier: Programming Language :: Python :: 3
Classifier: Programming Language :: Python :: 3.7
Classifier: Programming Language :: Python :: 3.8
Classifier: Programming Language :: Python :: 3.9
Classifier: Programming Language :: Python :: 3.10
Classifier: Programming Language :: Python :: 3.11
Requires-Python: >=3.7
Requires-Dist: httpx
Requires-Dist: postgrest
Requires-Dist: pydantic
Requires-Dist: requests
